Metadata-Version: 2.2
Name: botsheets
Version: 0.1.1
Summary: Class integrate with google sheets for RPA
Home-page: https://github.com/botlorien/botsheets
Author: Ben-Hur P. B. Santos
Author-email: botlorien@gmail.com
Classifier: Programming Language :: Python :: 3
Classifier: License :: OSI Approved :: MIT License
Classifier: Operating System :: OS Independent
Requires-Python: >=3.10
License-File: LICENSE
Requires-Dist: pandas
Requires-Dist: gspread
Requires-Dist: oauth2client
Requires-Dist: botenv
Dynamic: author
Dynamic: author-email
Dynamic: classifier
Dynamic: description
Dynamic: description-content-type
Dynamic: home-page
Dynamic: requires-dist
Dynamic: requires-python
Dynamic: summary
